Geanina_first_project/__init__.py
Geanina_first_project-0.1.0.dist-info/METADATA
Geanina_first_project-0.1.0.dist-info/WHEEL
Geanina_first_project-0.1.0.dist-info/top_level.txt
Geanina_first_project-0.1.0.dist-info/RECORD
