Metadata-Version: 2.1
Name: Geanina-first-project
Version: 0.1.0
Summary: Says Hello from Geanina
Author: Geanina
Author-email: gea.nina1166@gmail.com
License: UNKNOWN
Platform: UNKNOWN
Requires-Dist: dinosay
